simplejson-3.20.2.dist-info/WHEEL
simplejson-3.20.2.dist-info/top_level.txt
simplejson-3.20.2.dist-info/LICENSE.txt
simplejson-3.20.2.dist-info/METADATA
simplejson-3.20.2.dist-info/RECORD
simplejson/decoder.py
simplejson/ordered_dict.py
simplejson/_speedups.cpython-311-aarch64-linux-gnu.so
simplejson/tool.py
simplejson/encoder.py
simplejson/raw_json.py
simplejson/compat.py
simplejson/__init__.py
simplejson/scanner.py
simplejson/errors.py
simplejson/tests/test_namedtuple.py
simplejson/tests/test_indent.py
simplejson/tests/test_for_json.py
simplejson/tests/test_encode_for_html.py
simplejson/tests/test_errors.py
simplejson/tests/test_raw_json.py
simplejson/tests/test_encode_basestring_ascii.py
simplejson/tests/test_pass1.py
simplejson/tests/test_dump.py
simplejson/tests/test_scanstring.py
simplejson/tests/test_separators.py
simplejson/tests/test_pass2.py
simplejson/tests/test_decode.py
simplejson/tests/_cibw_runner.py
simplejson/tests/test_unicode.py
simplejson/tests/test_bigint_as_string.py
simplejson/tests/test_decimal.py
simplejson/tests/test_tool.py
simplejson/tests/test_recursion.py
simplejson/tests/test_fail.py
simplejson/tests/test_tuple.py
simplejson/tests/test_bitsize_int_as_string.py
simplejson/tests/test_default.py
simplejson/tests/test_float.py
simplejson/tests/test_speedups.py
simplejson/tests/test_pass3.py
simplejson/tests/test_iterable.py
simplejson/tests/test_item_sort_key.py
simplejson/tests/test_str_subclass.py
simplejson/tests/test_check_circular.py
simplejson/tests/__init__.py
simplejson/tests/test_subclass.py
